{
	"connect-wallet": "Conectar Billetera",
	"pools": "Pools",
	"Futures": "Futuros",
	"options": "Opciones",
	"beta": "beta",
	"governance": "Gobernanza",
	"bridge": "Puente",
	"docs": "Documentación",
	"stats": "Estadísticas",
	"airdrop": "AirDrop",
	"testnet": "Testnet",
	"more": "Más",
	"token": "Token",
	"team": "Equipo",
	"trade-to-earn": " 2 millones de DERI",
	"practice-to-earn": "Practica para ganar",
	"faq": "Preguntas Frecuentes",
	"code-audit": "Auditoría de código",
	"github": "Github",
	"guide": "Guía",
	"white-paper": "Libro Blanco",
	"promotional-event": "Eventos promocionales",
	"retired-pool": "Mercados y Pools Retiradas",
	"faucet": "Faucet",
	"use-deri": "USAR DERI",
	"unsupported-chain-id": "ID de cadena no soportada",
	"select-network": "Seleccione la red",
	"learn-more-about-wallet": "Más información sobre la creación de una billetera",
	"account": "Cuenta",
	"connected-with": "Conectado con",
	"copy-address": "Copiar la dirección",
	"view-on-bscscan": "Ver en Bscscan",
	"disconnect": "DESCONECTAR",
	"change-wallet": "Cambiar Billetera",
	"account-copied": "Dirección copiada",
	"powers": "Powers"
}